yaqc_bluesky/VERSION
yaqc_bluesky/__init__.py
yaqc_bluesky/__version__.py
yaqc_bluesky/_base.py
yaqc_bluesky/_device.py
yaqc_bluesky/_exceptions.py
yaqc_bluesky/_happi.py
yaqc_bluesky/_has_dependent.py
yaqc_bluesky/_has_mapping.py
yaqc_bluesky/_has_measure_trigger.py
yaqc_bluesky/_has_position.py
yaqc_bluesky/_is_discrete.py
yaqc_bluesky/_is_sensor.py
yaqc_bluesky/_property.py
yaqc_bluesky/_status.py
yaqc_bluesky/py.typed
yaqc_bluesky-2023.8.0.dist-info/entry_points.txt
yaqc_bluesky-2023.8.0.dist-info/LICENSE
yaqc_bluesky-2023.8.0.dist-info/WHEEL
yaqc_bluesky-2023.8.0.dist-info/METADATA
yaqc_bluesky-2023.8.0.dist-info/RECORD
