Metadata-Version: 2.1
Name: yaqc-bluesky
Version: 2023.8.0
Summary: A bluesky interface to the yaq instrument control framework.
Home-page: https://github.com/bluesky/yaqc-bluesky
Author: Blaise Thompson
Author-email: blaise@untzag.com
Requires-Python: >3.7
Classifier: Development Status :: 3 - Alpha
Classifier: Intended Audience :: Science/Research
Classifier: License :: OSI Approved :: BSD License
Classifier: Natural Language :: English
Classifier: Programming Language :: Python :: 3
Classifier: Programming Language :: Python :: 3.7
Classifier: Programming Language :: Python :: 3.8
Classifier: Programming Language :: Python :: 3.9
Classifier: Topic :: Scientific/Engineering
Requires-Dist: yaqc>=2021.10.0
Requires-Dist: bluesky>=1.6.6
Requires-Dist: happi>=2.0.0
Requires-Dist: black ; extra == "dev"
Requires-Dist: pre-commit ; extra == "dev"
Requires-Dist: pytest ; extra == "dev"
Requires-Dist: yaqd_core ; extra == "dev"
Requires-Dist: yaqd_fakes>=2022.3.0 ; extra == "dev"
Requires-Dist: mypy ; extra == "dev"
Requires-Dist: databroker<2 ; extra == "dev"
Provides-Extra: dev
